mugs/__init__.py
mugs-0.0.1.dist-info/METADATA
mugs-0.0.1.dist-info/WHEEL
mugs-0.0.1.dist-info/top_level.txt
mugs-0.0.1.dist-info/RECORD
